training/__init__.py
training/attentions.py
training/commons.py
training/data_utils.py
training/fix_torch.py
training/functional_fixed.py
training/losses.py
training/mel_processing.py
training/misc.py
training/models.py
training/modules.py
training/preprocess.py
training/run.py
training/train.py
training/train_config.py
training/train_ms.py
training/transforms.py
training/utils.py
training/monotonic_align/__init__.py
training/monotonic_align/setup.py
training/text/__init__.py
training/text/cleaners.py
training/text/mappers.py
training/text/symbols.py
sunbird_vits-0.0.6a4.dist-info/METADATA
sunbird_vits-0.0.6a4.dist-info/WHEEL
sunbird_vits-0.0.6a4.dist-info/top_level.txt
sunbird_vits-0.0.6a4.dist-info/RECORD
