Metadata-Version: 2.1
Name: sunbird-vits
Version: 0.0.6a4
Summary: A reworking of the vits package with additional proceesing for sunbirdAI data
Home-page: https://github.com/SunbirdAI/vits
Author: Ali Hussein
Author-email: azawahry@sunbird.ai
License: CC-sharealike-2.0
